external_components/uart_tx/address_decoder.vhd
library ieee;
use ieee.std_logic_1164.all;

entity address_decoder is
 port (
  address_bus : in std_logic_vector(15 downto 0);
  xc000 : out std_logic;
  xc001 : out std_logic
 );
end address_decoder;

architecture Behavioral of address_decoder is

  signal common_15_msb : std_logic;

begin

  common_15_msb <= address_bus(15) AND address_bus(14) AND
                   (NOT address_bus(13)) AND (NOT address_bus(12)) AND
                   (NOT address_bus(11)) AND (NOT address_bus(10)) AND
                   (NOT address_bus(9)) AND (NOT address_bus(8)) AND
                   (NOT address_bus(7)) AND (NOT address_bus(6)) AND
                   (NOT address_bus(5)) AND (NOT address_bus(4)) AND
                   (NOT address_bus(3)) AND (NOT address_bus(2)) AND
                   (NOT address_bus(1));

  xc000 <= common_15_msb AND (NOT address_bus(0));

  xc001 <= common_15_msb AND address_bus(0);

end architecture;

external_components/uart_tx/tb_address_decoder.vhd
library ieee;
use ieee.std_logic_1164.all;
use IEEE.numeric_std.all;

entity tb_address_decoder is
end tb_address_decoder;

architecture test_bench of tb_address_decoder is

  component address_decoder is
    port (
     address_bus : in std_logic_vector(15 downto 0);
     xc000 : out std_logic;
     xc001 : out std_logic
    );
  end component;

  signal address_bus : std_logic_vector(15 downto 0);
  signal xc000, xc001 : std_logic;

begin

  used_address_decoder : address_decoder port map(
    address_bus => address_bus,
    xc000 => xc000,
    xc001 => xc001
  );

  process
  begin
    address_bus <= "0000000000000000";

    for i in 0 to 65535 loop
       wait for 10 ns;
       address_bus <= std_logic_vector(unsigned(address_bus)+1);
    end loop;

    wait;
  end process;

end architecture;

external_components/uart_tx/tb_address_decoder.vcd
$date
  Mon Feb  1 19:58:51 2021
$end
$version
  GHDL v0
$end
$timescale
  1 fs
$end
$scope module standard $end
$upscope $end
$scope module std_logic_1164 $end
$upscope $end
$scope module numeric_std $end
$upscope $end
$scope module tb_address_decoder $end
$var reg 16 ! address_bus[15:0] $end
$var reg 1 " xc000 $end
$var reg 1 # xc001 $end
$scope module used_address_decoder $end
$var reg 16 $ address_bus[15:0] $end
$var reg 1 % xc000 $end
$var reg 1 & xc001 $end
$var reg 1 ' common_15_msb $end
$upscope $end
$upscope $end
$enddefinitions $end
#0
b0000000000000000 !
0"
0#
b0000000000000000 $
0%
0&
0'
#10000000
b0000000000000001 !
b0000000000000001 $
#20000000
b0000000000000010 !
b0000000000000010 $
#30000000
b0000000000000011 !
b0000000000000011 $
#40000000
b0000000000000100 !
b0000000000000100 $
#50000000
b0000000000000101 !
b0000000000000101 $
#60000000
b0000000000000110 !
b0000000000000110 $
#70000000
b0000000000000111 !
b0000000000000111 $
#80000000
b0000000000001000 !
b0000000000001000 $
#90000000
b0000000000001001 !
b0000000000001001 $
#100000000
b0000000000001010 !
b0000000000001010 $
#110000000
b0000000000001011 !
b0000000000001011 $
#120000000
b0000000000001100 !
b0000000000001100 $
#130000000
b0000000000001101 !
b0000000000001101 $
#140000000
b0000000000001110 !
b0000000000001110 $
#150000000
b0000000000001111 !
b0000000000001111 $
#160000000
b0000000000010000 !
b0000000000010000 $
#170000000
b0000000000010001 !
b0000000000010001 $
#180000000
b0000000000010010 !
b0000000000010010 $
#190000000
b0000000000010011 !
b0000000000010011 $
#200000000
b0000000000010100 !
b0000000000010100 $
#210000000
b0000000000010101 !
b0000000000010101 $
#220000000
b0000000000010110 !
b0000000000010110 $
#230000000
b0000000000010111 !
b0000000000010111 $
#240000000
b0000000000011000 !
b0000000000011000 $
#250000000
b0000000000011001 !
b0000000000011001 $
#260000000
b0000000000011010 !
b0000000000011010 $
#270000000
b0000000000011011 !
b0000000000011011 $
#280000000
b0000000000011100 !
b0000000000011100 $
#290000000
b0000000000011101 !
b0000000000011101 $
#300000000
b0000000000011110 !
b0000000000011110 $
#310000000
b0000000000011111 !
b0000000000011111 $
#320000000
b0000000000100000 !
b0000000000100000 $
#330000000
b0000000000100001 !
b0000000000100001 $
#340000000
b0000000000100010 !
b0000000000100010 $
#350000000
b0000000000100011 !
b0000000000100011 $
#360000000
b0000000000100100 !
b0000000000100100 $
#370000000
b0000000000100101 !
b0000000000100101 $
#380000000
b0000000000100110 !
b0000000000100110 $
#390000000
b0000000000100111 !
b0000000000100111 $
#400000000
b0000000000101000 !
b0000000000101000 $
#410000000
b0000000000101001 !
b0000000000101001 $
#420000000
b0000000000101010 !
b0000000000101010 $
#430000000
b0000000000101011 !
b0000000000101011 $
#440000000
b0000000000101100 !
b0000000000101100 $
#450000000
b0000000000101101 !
b0000000000101101 $
#460000000
b0000000000101110 !
b0000000000101110 $
#470000000
b0000000000101111 !
b0000000000101111 $
#480000000
b0000000000110000 !
b0000000000110000 $
#490000000
b0000000000110001 !
b0000000000110001 $
#500000000
b0000000000110010 !
b0000000000110010 $
#510000000
b0000000000110011 !
b0000000000110011 $
#520000000
b0000000000110100 !
b0000000000110100 $
#530000000
b0000000000110101 !
b0000000000110101 $
#540000000
b0000000000110110 !
b0000000000110110 $
#550000000
b0000000000110111 !
b0000000000110111 $
#560000000
b0000000000111000 !
b0000000000111000 $
#570000000
b0000000000111001 !
b0000000000111001 $
#580000000
b0000000000111010 !
b0000000000111010 $
#590000000
b0000000000111011 !
b0000000000111011 $
#600000000
b0000000000111100 !
b0000000000111100 $
#610000000
b0000000000111101 !
b0000000000111101 $
#620000000
b0000000000111110 !
b0000000000111110 $
#630000000
b0000000000111111 !
b0000000000111111 $
#640000000
b0000000001000000 !
b0000000001000000 $
#650000000
b0000000001000001 !
b0000000001000001 $
#660000000
b0000000001000010 !
b0000000001000010 $
#670000000
b0000000001000011 !
b0000000001000011 $
#680000000
b0000000001000100 !
b0000000001000100 $
#690000000
b0000000001000101 !
b0000000001000101 $
#700000000
b0000000001000110 !
b0000000001000110 $
#710000000
b0000000001000111 !
b0000000001000111 $
#720000000
b0000000001001000 !
b0000000001001000 $
#730000000
b0000000001001001 !
b0000000001001001 $
#740000000
b0000000001001010 !
b0000000001001010 $
#750000000
b0000000001001011 !
b0000000001001011 $
#760000000
b0000000001001100 !
b0000000001001100 $
#770000000
b0000000001001101 !
b0000000001001101 $
#780000000
b0000000001001110 !
b0000000001001110 $
#790000000
b0000000001001111 !
b0000000001001111 $
#800000000
b0000000001010000 !
b0000000001010000 $
#810000000
b0000000001010001 !
b0000000001010001 $
#820000000
b0000000001010010 !
b0000000001010010 $
#830000000
b0000000001010011 !
b0000000001010011 $
#840000000
b0000000001010100 !
b0000000001010100 $
#850000000
b0000000001010101 !
b0000000001010101 $
#860000000
b0000000001010110 !
b0000000001010110 $
#870000000
b0000000001010111 !
b0000000001010111 $
#880000000
b0000000001011000 !
b0000000001011000 $
#890000000
b0000000001011001 !
b0000000001011001 $
#900000000
b0000000001011010 !
b0000000001011010 $
#910000000
b0000000001011011 !
b0000000001011011 $
#920000000
b0000000001011100 !
b0000000001011100 $
#930000000
b0000000001011101 !
b0000000001011101 $
#940000000
b0000000001011110 !
b0000000001011110 $
#950000000
b0000000001011111 !
b0000000001011111 $
#960000000
b0000000001100000 !
b0000000001100000 $
#970000000
b0000000001100001 !
b0000000001100001 $
#980000000
b0000000001100010 !
b0000000001100010 $
#990000000
b0000000001100011 !
b0000000001100011 $
#1000000000
b0000000001100100 !
b0000000001100100 $
#1010000000
b0000000001100101 !
b0000000001100101 $
#1020000000
b0000000001100110 !
b0000000001100110 $
#1030000000
b0000000001100111 !
b0000000001100111 $
#1040000000
b0000000001101000 !
b0000000001101000 $
#1050000000
b0000000001101001 !
b0000000001101001 $
#1060000000
b0000000001101010 !
b0000000001101010 $
#1070000000
b0000000001101011 !
b0000000001101011 $
#1080000000
b0000000001101100 !
b0000000001101100 $
#1090000000
b0000000001101101 !
b0000000001101101 $
#1100000000
b0000000001101110 !
b0000000001101110 $
#1110000000
b0000000001101111 !
b0000000001101111 $
#1120000000
b0000000001110000 !
b0000000001110000 $
#1130000000
b0000000001110001 !
b0000000001110001 $
#1140000000
b0000000001110010 !
b0000000001110010 $
#1150000000
b0000000001110011 !
b0000000001110011 $
#1160000000
b0000000001110100 !
b0000000001110100 $
#1170000000
b0000000001110101 !
b0000000001110101 $
#1180000000
b0000000001110110 !
b0000000001110110 $
#1190000000
b0000000001110111 !
b0000000001110111 $
#1200000000
b0000000001111000 !
b0000000001111000 $
#1210000000
b0000000001111001 !
b0000000001111001 $
#1220000000
b0000000001111010 !
b0000000001111010 $
#1230000000
b0000000001111011 !
b0000000001111011 $
#1240000000
b0000000001111100 !
b0000000001111100 $
#1250000000
b0000000001111101 !
b0000000001111101 $
#1260000000
b0000000001111110 !
b0000000001111110 $
#1270000000
b0000000001111111 !
b0000000001111111 $
#1280000000
b0000000010000000 !
b0000000010000000 $
#1290000000
b0000000010000001 !
b0000000010000001 $
#1300000000
b0000000010000010 !
b0000000010000010 $
#1310000000
b0000000010000011 !
b0000000010000011 $
#1320000000
b0000000010000100 !
b0000000010000100 $
#1330000000
b0000000010000101 !
b0000000010000101 $
#1340000000
b0000000010000110 !
b0000000010000110 $
#1350000000
b0000000010000111 !
b0000000010000111 $
#1360000000
b0000000010001000 !
b0000000010001000 $
#1370000000
b0000000010001001 !
b0000000010001001 $
#1380000000
b0000000010001010 !
b0000000010001010 $
#1390000000
b0000000010001011 !
b0000000010001011 $
#1400000000
b0000000010001100 !
b0000000010001100 $
#1410000000
b0000000010001101 !
b0000000010001101 $
#1420000000
b0000000010001110 !
b0000000010001110 $
#1430000000
b0000000010001111 !
b0000000010001111 $
#1440000000
b0000000010010000 !
b0000000010010000 $
#1450000000
b0000000010010001 !
b0000000010010001 $
#1460000000
b0000000010010010 !
b0000000010010010 $
#1470000000
b0000000010010011 !
b0000000010010011 $
#1480000000
b0000000010010100 !
b0000000010010100 $
#1490000000
b0000000010010101 !
b0000000010010101 $
#1500000000
b0000000010010110 !
b0000000010010110 $
#1510000000
b0000000010010111 !
b0000000010010111 $
#1520000000
b0000000010011000 !
b0000000010011000 $
#1530000000
b0000000010011001 !
b0000000010011001 $
#1540000000
b0000000010011010 !
b0000000010011010 $
#1550000000
b0000000010011011 !
b0000000010011011 $
#1560000000
b0000000010011100 !
b0000000010011100 $
#1570000000
b0000000010011101 !
b0000000010011101 $
#1580000000
b0000000010011110 !
b0000000010011110 $
#1590000000
b0000000010011111 !
b0000000010011111 $
#1600000000
b0000000010100000 !
b0000000010100000 $
#1610000000
b0000000010100001 !
b0000000010100001 $
#1620000000
b0000000010100010 !
b0000000010100010 $
#1630000000
b0000000010100011 !
b0000000010100011 $
#1640000000
b0000000010100100 !
b0000000010100100 $
#1650000000
b0000000010100101 !
b0000000010100101 $
#1660000000
b0000000010100110 !
b0000000010100110 $
#1670000000
b0000000010100111 !
b0000000010100111 $
#1680000000
b0000000010101000 !
b0000000010101000 $
#1690000000
b0000000010101001 !
b0000000010101001 $
#1700000000
b0000000010101010 !
b0000000010101010 $
#1710000000
b0000000010101011 !
b0000000010101011 $
#1720000000
b0000000010101100 !
b0000000010101100 $
#1730000000
b0000000010101101 !
b0000000010101101 $
#1740000000
b0000000010101110 !
b0000000010101110 $
#1750000000
b0000000010101111 !
b0000000010101111 $
#1760000000
b0000000010110000 !
b0000000010110000 $
#1770000000
b0000000010110001 !
b0000000010110001 $
#1780000000
b0000000010110010 !
b0000000010110010 $
#1790000000
b0000000010110011 !
b0000000010110011 $
#1800000000
b0000000010110100 !
b0000000010110100 $
#1810000000
b0000000010110101 !
b0000000010110101 $
#1820000000
b0000000010110110 !
b0000000010110110 $
#1830000000
b0000000010110111 !
b0000000010110111 $
#1840000000
b0000000010111000 !
b0000000010111000 $
#1850000000
b0000000010111001 !
b0000000010111001 $
#1860000000
b0000000010111010 !
b0000000010111010 $
#1870000000
b0000000010111011 !
b0000000010111011 $
#1880000000
b0000000010111100 !
b0000000010111100 $
#1890000000
b0000000010111101 !
b0000000010111101 $
#1900000000
b0000000010111110 !
b0000000010111110 $
#1910000000
b0000000010111111 !
b0000000010111111 $
#1920000000
b0000000011000000 !
b0000000011000000 $
#1930000000
b0000000011000001 !
b0000000011000001 $
#1940000000
b0000000011000010 !
b0000000011000010 $
#1950000000
b0000000011000011 !
b0000000011000011 $
#1960000000
b0000000011000100 !
b0000000011000100 $
#1970000000
b0000000011000101 !
b0000000011000101 $
#1980000000
b0000000011000110 !
b0000000011000110 $
#1990000000
b0000000011000111 !
b0000000011000111 $
#2000000000
b0000000011001000 !
b0000000011001000 $
#2010000000
b0000000011001001 !
b0000000011001001 $
#2020000000
b0000000011001010 !
b0000000011001010 $
#2030000000
b0000000011001011 !
b0000000011001011 $
#2040000000
b0000000011001100 !
b0000000011001100 $
#2050000000
b0000000011001101 !
b0000000011001101 $
#2060000000
b0000000011001110 !
b0000000011001110 $
#2070000000
b0000000011001111 !
b0000000011001111 $
#2080000000
b0000000011010000 !
b0000000011010000 $
#2090000000
b0000000011010001 !
b0000000011010001 $
#2100000000
b0000000011010010 !
b0000000011010010 $
#2110000000
b0000000011010011 !
b0000000011010011 $
#2120000000
b0000000011010100 !
b0000000011010100 $
#2130000000
b0000000011010101 !
b0000000011010101 $
#2140000000
b0000000011010110 !
b0000000011010110 $
#2150000000
b0000000011010111 !
b0000000011010111 $
#2160000000
b0000000011011000 !
b0000000011011000 $
#2170000000
b0000000011011001 !
b0000000011011001 $
#2180000000
b0000000011011010 !
b0000000011011010 $
#2190000000
b0000000011011011 !
b0000000011011011 $
#2200000000
b0000000011011100 !
b0000000011011100 $
#2210000000
b0000000011011101 !
b0000000011011101 $
#2220000000
b0000000011011110 !
b0000000011011110 $
#2230000000
b0000000011011111 !
b0000000011011111 $
#2240000000
b0000000011100000 !
b0000000011100000 $
#2250000000
b0000000011100001 !
b0000000011100001 $
#2260000000
b0000000011100010 !
b0000000011100010 $
#2270000000
b0000000011100011 !
b0000000011100011 $
#2280000000
b0000000011100100 !
b0000000011100100 $
#2290000000
b0000000011100101 !
b0000000011100101 $
#2300000000
b0000000011100110 !
b0000000011100110 $
#2310000000
b0000000011100111 !
b0000000011100111 $
#2320000000
b0000000011101000 !
b0000000011101000 $
#2330000000
b0000000011101001 !
b0000000011101001 $
#2340000000
b0000000011101010 !
b0000000011101010 $
#2350000000
b0000000011101011 !
b0000000011101011 $
#2360000000
b0000000011101100 !
b0000000011101100 $
#2370000000
b0000000011101101 !
b0000000011101101 $
#2380000000
b0000000011101110 !
b0000000011101110 $
#2390000000
b0000000011101111 !
b0000000011101111 $
#2400000000
b0000000011110000 !
b0000000011110000 $
#2410000000
b0000000011110001 !
b0000000011110001 $
#2420000000
b0000000011110010 !
b0000000011110010 $
#2430000000
b0000000011110011 !
b0000000011110011 $
#2440000000
b0000000011110100 !
b0000000011110100 $
#2450000000
b0000000011110101 !
b0000000011110101 $
#2460000000
b0000000011110110 !
b0000000011110110 $
#2470000000
b0000000011110111 !
b0000000011110111 $
#2480000000
b0000000011111000 !
b0000000011111000 $
#2490000000
b0000000011111001 !
b0000000011111001 $
#2500000000
b0000000011111010 !
b0000000011111010 $
#2510000000
b0000000011111011 !
b0000000011111011 $
#2520000000
b0000000011111100 !
b0000000011111100 $
#2530000000
b0000000011111101 !
b0000000011111101 $
#2540000000
b0000000011111110 !
b0000000011111110 $
#2550000000
b0000000011111111 !
b0000000011111111 $
#2560000000
b0000000100000000 !
b0000000100000000 $
#2570000000
b0000000100000001 !
b0000000100000001 $
#2580000000
b0000000100000010 !
b0000000100000010 $
#2590000000
b0000000100000011 !
b0000000100000011 $
#2600000000
b0000000100000100 !
b0000000100000100 $
#2610000000
b0000000100000101 !
b0000000100000101 $
#2620000000
b0000000100000110 !
b0000000100000110 $
#2630000000
b0000000100000111 !
b0000000100000111 $
#2640000000
b0000000100001000 !
b0000000100001000 $
#2650000000
b0000000100001001 !
b0000000100001001 $
#2660000000
b0000000100001010 !
b0000000100001010 $
#2670000000
b0000000100001011 !
b0000000100001011 $
#2680000000
b0000000100001100 !
b0000000100001100 $
#2690000000
b0000000100001101 !
b0000000100001101 $
#2700000000
b0000000100001110 !
b0000000100001110 $
#2710000000
b0000000100001111 !
b0000000100001111 $
#2720000000
b0000000100010000 !
b0000000100010000 $
#2730000000
b0000000100010001 !
b0000000100010001 $
#2740000000
b0000000100010010 !
b0000000100010010 $
#2750000000
b0000000100010011 !
b0000000100010011 $
#2760000000
b0000000100010100 !
b0000000100010100 $
#2770000000
b0000000100010101 !
b0000000100010101 $
#2780000000
b0000000100010110 !
b0000000100010110 $
#2790000000
b0000000100010111 !
b0000000100010111 $
#2800000000
b0000000100011000 !
b0000000100011000 $
#2810000000
b0000000100011001 !
b0000000100011001 $
#2820000000
b0000000100011010 !
b0000000100011010 $
#2830000000
b0000000100011011 !
b0000000100011011 $
#2840000000
b0000000100011100 !
b0000000100011100 $
#2850000000
b0000000100011101 !
b0000000100011101 $
#2860000000
b0000000100011110 !
b0000000100011110 $
#2870000000
b0000000100011111 !
b0000000100011111 $
#2880000000
b0000000100100000 !
b0000000100100000 $
#2890000000
b0000000100100001 !
b0000000100100001 $
#2900000000
b0000000100100010 !
b0000000100100010 $
#2910000000
b0000000100100011 !
b0000000100100011 $
#2920000000
b0000000100100100 !
b0000000100100100 $
#2930000000
b0000000100100101 !
b0000000100100101 $
#2940000000
b0000000100100110 !
b0000000100100110 $
#2950000000
b0000000100100111 !
b0000000100100111 $
#2960000000
b0000000100101000 !
b0000000100101000 $
#2970000000
b0000000100101001 !
b0000000100101001 $
#2980000000
b0000000100101010 !
b0000000100101010 $
#2990000000
b0000000100101011 !
b0000000100101011 $
#3000000000
b0000000100101100 !
b0000000100101100 $
#3010000000
b0000000100101101 !
b0000000100101101 $
#3020000000
b0000000100101110 !
b0000000100101110 $
#3030000000
b0000000100101111 !
b0000000100101111 $
#3040000000
b0000000100110000 !
b0000000100110000 $
#3050000000
b0000000100110001 !
b0000000100110001 $
#3060000000
b0000000100110010 !
b0000000100110010 $
#3070000000
b0000000100110011 !
b0000000100110011 $
#3080000000
b0000000100110100 !
b0000000100110100 $
#3090000000
b0000000100110101 !
b0000000100110101 $
#3100000000
b0000000100110110 !
b0000000100110110 $
#3110000000
b0000000100110111 !
b0000000100110111 $
#3120000000
b0000000100111000 !
b0000000100111000 $
#3130000000
b0000000100111001 !
b0000000100111001 $
#3140000000
b0000000100111010 !
b0000000100111010 $
#3150000000
b0000000100111011 !
b0000000100111011 $
#3160000000
b0000000100111100 !
b0000000100111100 $
#3170000000
b0000000100111101 !
b0000000100111101 $
#3180000000
b0000000100111110 !
b0000000100111110 $
#3190000000
b0000000100111111 !
b0000000100111111 $
#3200000000
b0000000101000000 !
b0000000101000000 $
#3210000000
b0000000101000001 !
b0000000101000001 $
#3220000000
b0000000101000010 !
b0000000101000010 $
#3230000000
b0000000101000011 !
b0000000101000011 $
#3240000000
b0000000101000100 !
b0000000101000100 $
#3250000000
b0000000101000101 !
b0000000101000101 $
#3260000000
b0000000101000110 !
b0000000101000110 $
#3270000000
b0000000101000111 !
b0000000101000111 $
#3280000000
b0000000101001000 !
b0000000101001000 $
#3290000000
b0000000101001001 !
b0000000101001001 $
#3300000000
b0000000101001010 !
b0000000101001010 $
#3310000000
b0000000101001011 !
b0000000101001011 $
#3320000000
b0000000101001100 !
b0000000101001100 $
#3330000000
b0000000101001101 !
b0000000101001101 $
#3340000000
b0000000101001110 !
b0000000101001110 $
#3350000000
b0000000101001111 !
b0000000101001111 $
#3360000000
b0000000101010000 !
b0000000101010000 $
#3370000000
b0000000101010001 !
b0000000101010001 $
#3380000000
b0000000101010010 !
b0000000101010010 $
#3390000000
b0000000101010011 !
b0000000101010011 $
#3400000000
b0000000101010100 !
b0000000101010100 $
#3410000000
b0000000101010101 !
b0000000101010101 $
#3420000000
b0000000101010110 !
b0000000101010110 $
#3430000000
b0000000101010111 !
b0000000101010111 $
#3440000000
b0000000101011000 !
b0000000101011000 $
#3450000000
b0000000101011001 !
b0000000101011001 $
#3460000000
b0000000101011010 !
b0000000101011010 $
#3470000000
b0000000101011011 !
b0000000101011011 $
#3480000000
b0000000101011100 !
b0000000101011100 $
#3490000000
b0000000101011101 !
b0000000101011101 $
#3500000000
b0000000101011110 !
b0000000101011110 $
#3510000000
b0000000101011111 !
b0000000101011111 $
#3520000000
b0000000101100000 !
b0000000101100000 $
#3530000000
b0000000101100001 !
b0000000101100001 $
#3540000000
b0000000101100010 !
b0000000101100010 $
#3550000000
b0000000101100011 !
b0000000101100011 $
#3560000000
b0000000101100100 !
b0000000101100100 $
#3570000000
b0000000101100101 !
b0000000101100101 $
#3580000000
b0000000101100110 !
b0000000101100110 $
#3590000000
b0000000101100111 !
b0000000101100111 $
#3600000000
b0000000101101000 !
b0000000101101000 $
#3610000000
b0000000101101001 !
b0000000101101001 $
#3620000000
b0000000101101010 !
b0000000101101010 $
#3630000000
b0000000101101011 !
b0000000101101011 $
#3640000000
b0000000101101100 !
b0000000101101100 $
#3650000000
b0000000101101101 !
b0000000101101101 $
#3660000000
b0000000101101110 !
b0000000101101110 $
#3670000000
b0000000101101111 !
b0000000101101111 $
#3680000000
b0000000101110000 !
b0000000101110000 $
#3690000000
b0000000101110001 !
b0000000101110001 $
#3700000000
b0000000101110010 !
b0000000101110010 $
#3710000000
b0000000101110011 !
b0000000101110011 $
#3720000000
b0000000101110100 !
b0000000101110100 $
#3730000000
b0000000101110101 !
b0000000101110101 $
#3740000000
b0000000101110110 !
b0000000101110110 $
#3750000000
b0000000101110111 !
b0000000101110111 $
#3760000000
b0000000101111000 !
b0000000101111000 $
#3770000000
b0000000101111001 !
b0000000101111001 $
#3780000000
b0000000101111010 !
b0000000101111010 $
#3790000000
b0000000101111011 !
b0000000101111011 $
#3800000000
b0000000101111100 !
b0000000101111100 $
#3810000000
b0000000101111101 !
b0000000101111101 $
#3820000000
b0000000101111110 !
b0000000101111110 $
#3830000000
b0000000101111111 !
b0000000101111111 $
#3840000000
b0000000110000000 !
b0000000110000000 $
#3850000000
b0000000110000001 !
b0000000110000001 $
#3860000000
b0000000110000010 !
b0000000110000010 $
#3870000000
b0000000110000011 !
b0000000110000011 $
#3880000000
b0000000110000100 !
b0000000110000100 $
#3890000000
b0000000110000101 !
b0000000110000101 $
#3900000000
b0000000110000110 !
b0000000110000110 $
#3910000000
b0000000110000111 !
b0000000110000111 $
#3920000000
b0000000110001000 !
b0000000110001000 $
#3930000000
b0000000110001001 !
b0000000110001001 $
#3940000000
b0000000110001010 !
b0000000110001010 $
#3950000000
b0000000110001011 !
b0000000110001011 $
#3960000000
b0000000110001100 !
b0000000110001100 $
#3970000000
b0000000110001101 !
b0000000110001101 $
#3980000000
b0000000110001110 !
b0000000110001110 $
#3990000000
b0000000110001111 !
b0000000110001111 $
#4000000000
b0000000110010000 !
b0000000110010000 $
#4010000000
b0000000110010001 !
b0000000110010001 $
#4020000000
b0000000110010010 !
b0000000110010010 $
#4030000000
b0000000110010011 !
b0000000110010011 $
#4040000000
b0000000110010100 !
b0000000110010100 $
#4050000000
b0000000110010101 !
b0000000110010101 $
#4060000000
b0000000110010110 !
b0000000110010110 $
#4070000000
b0000000110010111 !
b0000000110010111 $
#4080000000
b0000000110011000 !
b0000000110011000 $
#4090000000
b0000000110011001 !
b0000000110011001 $
#4100000000
b0000000110011010 !
b0000000110011010 $
#4110000000
b0000000110011011 !
b0000000110011011 $
#4120000000
b0000000110011100 !
b0000000110011100 $
#4130000000
b0000000110011101 !
b0000000110011101 $
#4140000000
b0000000110011110 !
b0000000110011110 $
#4150000000
b0000000110011111 !
b0000000110011111 $
#4160000000
b0000000110100000 !
b0000000110100000 $
#4170000000
b0000000110100001 !
b0000000110100001 $
#4180000000
b0000000110100010 !
b0000000110100010 $
#4190000000
b0000000110100011 !
b0000000110100011 $
#4200000000
b0000000110100100 !
b0000000110100100 $
#4210000000
b0000000110100101 !
b0000000110100101 $
#4220000000
b0000000110100110 !
b0000000110100110 $
#4230000000
b0000000110100111 !
b0000000110100111 $
#4240000000
b0000000110101000 !
b0000000110101000 $
#4250000000
b0000000110101001 !
b0000000110101001 $
#4260000000
b0000000110101010 !
b0000000110101010 $
#4270000000
b0000000110101011 !
b0000000110101011 $
#4280000000
b0000000110101100 !
b0000000110101100 $
#4290000000
b0000000110101101 !
b0000000110101101 $
#4300000000
b0000000110101110 !
b0000000110101110 $
#4310000000
b0000000110101111 !
b0000000110101111 $
#4320000000
b0000000110110000 !
b0000000110110000 $
#4330000000
b0000000110110001 !
b0000000110110001 $
#4340000000
b0000000110110010 !
b0000000110110010 $
#4350000000
b0000000110110011 !
b0000000110110011 $
#4360000000
b0000000110110100 !
b0000000110110100 $
#4370000000
b0000000110110101 !
b0000000110110101 $
#4380000000
b0000000110110110 !
b0000000110110110 $
#4390000000
b0000000110110111 !
b0000000110110111 $
#4400000000
b0000000110111000 !
b0000000110111000 $
#4410000000
b0000000110111001 !
b0000000110111001 $
#4420000000
b0000000110111010 !
b0000000110111010 $
#4430000000
b0000000110111011 !
b0000000110111011 $
#4440000000
b0000000110111100 !
b0000000110111100 $
#4450000000
b0000000110111101 !
b0000000110111101 $
#4460000000
b0000000110111110 !
b0000000110111110 $
#4470000000
b0000000110111111 !
b0000000110111111 $
#4480000000
b0000000111000000 !
b0000000111000000 $
#4490000000
b0000000111000001 !
b0000000111000001 $
#4500000000
b0000000111000010 !
b0000000111000010 $
#4510000000
b0000000111000011 !
b0000000111000011 $
#4520000000
b0000000111000100 !
b0000000111000100 $
#4530000000
b0000000111000101 !
b0000000111000101 $
#4540000000
b0000000111000110 !
b0000000111000110 $
#4550000000
b0000000111000111 !
b0000000111000111 $
#4560000000
b0000000111001000 !
b0000000111001000 $
#4570000000
b0000000111001001 !
b0000000111001001 $
#4580000000
b0000000111001010 !
b0000000111001010 $
#4590000000
b0000000111001011 !
b0000000111001011 $
#4600000000
b0000000111001100 !
b0000000111001100 $
#4610000000
b0000000111001101 !
b0000000111001101 $
#4620000000
b0000000111001110 !
b0000000111001110 $
#4630000000
b0000000111001111 !
b0000000111001111 $
#4640000000
b0000000111010000 !
b0000000111010000 $
#4650000000
b0000000111010001 !
b0000000111010001 $
#4660000000
b0000000111010010 !
b0000000111010010 $
#4670000000
b0000000111010011 !
b0000000111010011 $
#4680000000
b0000000111010100 !
b0000000111010100 $
#4690000000
b0000000111010101 !
b0000000111010101 $
#4700000000
b0000000111010110 !
b0000000111010110 $
#4710000000
b0000000111010111 !
b0000000111010111 $
#4720000000
b0000000111011000 !
b0000000111011000 $
#4730000000
b0000000111011001 !
b0000000111011001 $
#4740000000
b0000000111011010 !
b0000000111011010 $
#4750000000
b0000000111011011 !
b0000000111011011 $
#4760000000
b0000000111011100 !
b0000000111011100 $
#4770000000
b0000000111011101 !
b0000000111011101 $
#4780000000
b0000000111011110 !
b0000000111011110 $
#4790000000
b0000000111011111 !
b0000000111011111 $
#4800000000
b0000000111100000 !
b0000000111100000 $
#4810000000
b0000000111100001 !
b0000000111100001 $
#4820000000
b0000000111100010 !
b0000000111100010 $
#4830000000
b0000000111100011 !
b0000000111100011 $
#4840000000
b0000000111100100 !
b0000000111100100 $
#4850000000
b0000000111100101 !
b0000000111100101 $
#4860000000
b0000000111100110 !
b0000000111100110 $
#4870000000
b0000000111100111 !
b0000000111100111 $
#4880000000
b0000000111101000 !
b0000000111101000 $
#4890000000
b0000000111101001 !
b0000000111101001 $
#4900000000
b0000000111101010 !
b0000000111101010 $
#4910000000
b0000000111101011 !
b0000000111101011 $
#4920000000
b0000000111101100 !
b0000000111101100 $
#4930000000
b0000000111101101 !
b0000000111101101 $
#4940000000
b0000000111101110 !
b0000000111101110 $
#4950000000
b0000000111101111 !
b0000000111101111 $
#4960000000
b0000000111110000 !
b0000000111110000 $
#4970000000
b0000000111110001 !
b0000000111110001 $
#4980000000
b0000000111110010 !
b0000000111110010 $
#4990000000
b0000000111110011 !
b0000000111110011 $
#5000000000
b0000000111110100 !
b0000000111110100 $
#5010000000
b0000000111110101 !
b0000000111110101 $
#5020000000
b0000000111110110 !
b0000000111110110 $
#5030000000
b0000000111110111 !
b0000000111110111 $
#5040000000
b0000000111111000 !
b0000000111111000 $
#5050000000
b0000000111111001 !
b0000000111111001 $
#5060000000
b0000000111111010 !
b0000000111111010 $
#5070000000
b0000000111111011 !
b0000000111111011 $
#5080000000
b0000000111111100 !
b0000000111111100 $
#5090000000
b0000000111111101 !
b0000000111111101 $
#5100000000
b0000000111111110 !
b0000000111111110 $
#5110000000
b0000000111111111 !
b0000000111111111 $
#5120000000
b0000001000000000 !
b0000001000000000 $
#5130000000
b0000001000000001 !
b0000001000000001 $
#5140000000
b0000001000000010 !
b0000001000000010 $
#5150000000
b0000001000000011 !
b0000001000000011 $
#5160000000
b0000001000000100 !
b0000001000000100 $
#5170000000
b0000001000000101 !
b0000001000000101 $
#5180000000
b0000001000000110 !
b0000001000000110 $
#5190000000
b0000001000000111 !
b0000001000000111 $
#5200000000
b0000001000001000 !
b0000001000001000 $
#5210000000
b0000001000001001 !
b0000001000001001 $
#5220000000
b0000001000001010 !
b0000001000001010 $
#5230000000
b0000001000001011 !
b0000001000001011 $
#5240000000
b0000001000001100 !
b0000001000001100 $
#5250000000
b0000001000001101 !
b0000001000001101 $
#5260000000
b0000001000001110 !
b0000001000001110 $
#5270000000
b0000001000001111 !
b0000001000001111 $
#5280000000
b0000001000010000 !
b0000001000010000 $
#5290000000
b0000001000010001 !
b0000001000010001 $
#5300000000
b0000001000010010 !
b0000001000010010 $
#5310000000
b0000001000010011 !
b0000001000010011 $
#5320000000
b0000001000010100 !
b0000001000010100 $
#5330000000
b0000001000010101 !
b0000001000010101 $
#5340000000
b0000001000010110 !
b0000001000010110 $
#5350000000
b0000001000010111 !
b0000001000010111 $
#5360000000
b0000001000011000 !
b0000001000011000 $
