CPU/PC/half_adder.vhd
library ieee;
use ieee.std_logic_1164.all;

entity half_adder is
	port
	(
			a: in std_logic;
			c_in: in std_logic;
			o: out std_logic;
			c_out: out std_logic
	 );
end half_adder;

architecture Behavioral of half_adder is
begin
	o <= a XOR c_in;
	c_out <= a AND c_in;
end Behavioral;

external_components/uart_tx/counter_4_bits.vhd
library ieee;
use ieee.std_logic_1164.all;

entity counter_4_bits is
  port (
    clk : in std_logic;
    clk_enable : in std_logic;
    reset : in std_logic;
    counter_value : out std_logic_vector(3 downto 0)
  );
end counter_4_bits;

architecture Behavioral of counter_4_bits is

  component half_adder is
    port
  	(
  			a: in std_logic;
  			c_in: in std_logic;
  			o: out std_logic;
  			c_out: out std_logic
  	 );
  end component;

  signal current_value : std_logic_vector(3 downto 0) := "1011";
  signal next_value : std_logic_vector(3 downto 0);
  signal carries : std_logic_vector(2 downto 0);

begin

  counter_value <= current_value;

  ha0 : half_adder port map(
    a => current_value(0),
    c_in => '1',
    o => next_value(0),
    c_out => carries(0)
  );

  ha1 : half_adder port map(
    a => current_value(1),
    c_in => carries(0),
    o => next_value(1),
    c_out => carries(1)
  );

  ha2 : half_adder port map(
    a => current_value(2),
    c_in => carries(1),
    o => next_value(2),
    c_out => carries(2)
  );

  ha3 : half_adder port map(
    a => current_value(3),
    c_in => carries(2),
    o => next_value(3),
    c_out => open
  );

  process(clk)
  begin
    if rising_edge(clk) then
      if reset='1' then
        current_value <= "0000";
      else
        if clk_enable='1' then
          current_value <= next_value;
        end if;
      end if;
    end if;
  end process;

end architecture;

external_components/uart_tx/tb_counter_4_bits.vhd
library ieee;
use ieee.std_logic_1164.all;
use IEEE.numeric_std.all;

entity tb_counter_4_bits is
end tb_counter_4_bits;

architecture test_bench of tb_counter_4_bits is

  component counter_4_bits is
    port (
      clk : in std_logic;
      clk_enable : in std_logic;
      reset : in std_logic;
      counter_value : out std_logic_vector(3 downto 0)
    );
  end component;

  signal clk_enable, reset, clk : std_logic;
  signal counter_value : std_logic_vector(3 downto 0);

begin

  used_counter_4_bits : counter_4_bits port map(
    clk => clk,
    clk_enable => clk_enable,
    reset => reset,
    counter_value => counter_value
  );

  process
  begin
    clk <= '0';
    wait for 5 ns;
    clk <= '1';
    wait for 5 ns;
  end process;

  process
  begin
    wait for 200 ns;

    reset <= '0';
    clk_enable <= '0';
    wait for 10 ns;

    reset <= '1';
    wait for 100 ns;

    clk_enable <= '1';
    wait for 100 ns;

    reset <= '0';
    wait for 200 ns;

    clk_enable <= '0';
    wait for 100 ns;

    wait;
  end process;

end architecture;

external_components/uart_tx/tb_counter_4_bits.vcd
$date
  Mon Feb  1 21:12:19 2021
$end
$version
  GHDL v0
$end
$timescale
  1 fs
$end
$scope module standard $end
$upscope $end
$scope module std_logic_1164 $end
$upscope $end
$scope module numeric_std $end
$upscope $end
$scope module tb_counter_4_bits $end
$var reg 1 ! clk_enable $end
$var reg 1 " reset $end
$var reg 1 # clk $end
$var reg 4 $ counter_value[3:0] $end
$scope module used_counter_4_bits $end
$var reg 1 % clk $end
$var reg 1 & clk_enable $end
$var reg 1 ' reset $end
$var reg 4 ( counter_value[3:0] $end
$var reg 4 ) current_value[3:0] $end
$var reg 4 * next_value[3:0] $end
$var reg 3 + carries[2:0] $end
$scope module ha0 $end
$var reg 1 , a $end
$var reg 1 - c_in $end
$var reg 1 . o $end
$var reg 1 / c_out $end
$upscope $end
$scope module ha1 $end
$var reg 1 0 a $end
$var reg 1 1 c_in $end
$var reg 1 2 o $end
$var reg 1 3 c_out $end
$upscope $end
$scope module ha2 $end
$var reg 1 4 a $end
$var reg 1 5 c_in $end
$var reg 1 6 o $end
$var reg 1 7 c_out $end
$upscope $end
$scope module ha3 $end
$var reg 1 8 a $end
$var reg 1 9 c_in $end
$var reg 1 : o $end
$var reg 1 ; c_out $end
$upscope $end
$upscope $end
$upscope $end
$enddefinitions $end
#0
U!
U"
0#
bUUUU $
0%
U&
U'
bUUUU (
bUUUU )
bUUUU *
bUUU +
U,
1-
U.
U/
U0
U1
U2
U3
U4
U5
U6
U7
U8
U9
U:
U;
#5000000
1#
1%
#10000000
0#
0%
#15000000
1#
1%
#20000000
0#
0%
#25000000
1#
1%
#30000000
0#
0%
#35000000
1#
1%
#40000000
0#
0%
#45000000
1#
1%
#50000000
0#
0%
#55000000
1#
1%
#60000000
0#
0%
#65000000
1#
1%
#70000000
0#
0%
#75000000
1#
1%
#80000000
0#
0%
#85000000
1#
1%
#90000000
0#
0%
#95000000
1#
1%
#100000000
0#
0%
#105000000
1#
1%
#110000000
0#
0%
#115000000
1#
1%
#120000000
0#
0%
#125000000
1#
1%
#130000000
0#
0%
#135000000
1#
1%
#140000000
0#
0%
#145000000
1#
1%
#150000000
0#
0%
#155000000
1#
1%
#160000000
0#
0%
#165000000
1#
1%
#170000000
0#
0%
#175000000
1#
1%
#180000000
0#
0%
#185000000
1#
1%
#190000000
0#
0%
#195000000
1#
1%
#200000000
0!
0"
0#
0%
0&
0'
#205000000
1#
1%
#210000000
1"
0#
b0000 $
0%
1'
b0000 (
b0000 )
b0001 *
b000 +
0,
1.
0/
00
01
02
03
04
05
06
07
08
09
0:
0;
#215000000
1#
1%
#220000000
0#
0%
#225000000
1#
1%
#230000000
0#
0%
#235000000
1#
1%
#240000000
0#
0%
#245000000
1#
1%
#250000000
0#
0%
#255000000
1#
1%
#260000000
0#
0%
#265000000
1#
1%
#270000000
0#
0%
#275000000
1#
1%
#280000000
0#
0%
#285000000
1#
1%
#290000000
0#
0%
#295000000
1#
1%
#300000000
0#
0%
#305000000
1#
1%
#310000000
1!
0#
0%
1&
#315000000
1#
1%
#320000000
0#
0%
#325000000
1#
1%
#330000000
0#
0%
#335000000
1#
1%
#340000000
0#
0%
#345000000
1#
1%
#350000000
0#
0%
#355000000
1#
1%
#360000000
0#
0%
#365000000
1#
1%
#370000000
0#
0%
#375000000
1#
1%
#380000000
0#
0%
#385000000
1#
1%
#390000000
0#
0%
#395000000
1#
1%
#400000000
0#
0%
#405000000
1#
1%
#410000000
0"
0#
0%
0'
#415000000
1#
b0001 $
1%
b0001 (
b0001 )
b0010 *
b001 +
1,
0.
1/
11
12
#420000000
0#
0%
#425000000
1#
b0010 $
1%
b0010 (
b0010 )
b0011 *
b000 +
0,
1.
0/
10
01
12
03
05
06
#430000000
0#
0%
#435000000
1#
b0011 $
1%
b0011 (
b0011 )
b0100 *
b011 +
1,
0.
1/
11
02
13
15
16
#440000000
0#
0%
#445000000
1#
b0100 $
1%
b0100 (
b0100 )
b0101 *
b000 +
0,
1.
0/
00
01
02
03
14
05
16
07
09
0:
#450000000
0#
0%
#455000000
1#
b0101 $
1%
b0101 (
b0101 )
b0110 *
b001 +
1,
0.
1/
11
12
#460000000
0#
0%
#465000000
1#
b0110 $
1%
b0110 (
b0110 )
b0111 *
b000 +
0,
1.
0/
10
01
12
03
05
16
07
09
0:
#470000000
0#
0%
#475000000
1#
b0111 $
1%
b0111 (
b0111 )
b1000 *
b111 +
1,
0.
1/
11
02
13
15
06
17
19
1:
#480000000
0#
0%
#485000000
1#
b1000 $
1%
b1000 (
b1000 )
b1001 *
b000 +
0,
1.
0/
00
01
02
03
04
05
06
07
18
09
1:
0;
#490000000
0#
0%
#495000000
1#
b1001 $
1%
b1001 (
b1001 )
b1010 *
b001 +
1,
0.
1/
11
12
#500000000
0#
0%
#505000000
1#
b1010 $
1%
b1010 (
b1010 )
b1011 *
b000 +
0,
1.
0/
10
01
12
03
05
06
#510000000
0#
0%
#515000000
1#
b1011 $
1%
b1011 (
b1011 )
b1100 *
b011 +
1,
0.
1/
11
02
13
15
16
#520000000
0#
0%
#525000000
1#
b1100 $
1%
b1100 (
b1100 )
b1101 *
b000 +
0,
1.
0/
00
01
02
03
14
05
16
07
09
1:
0;
#530000000
0#
0%
#535000000
1#
b1101 $
1%
b1101 (
b1101 )
b1110 *
b001 +
1,
0.
1/
11
12
#540000000
0#
0%
#545000000
1#
b1110 $
1%
b1110 (
b1110 )
b1111 *
b000 +
0,
1.
0/
10
01
12
03
05
16
07
09
1:
0;
#550000000
0#
0%
#555000000
1#
b1111 $
1%
b1111 (
b1111 )
b0000 *
b111 +
1,
0.
1/
11
02
13
15
06
17
19
0:
1;
#560000000
0#
0%
#565000000
1#
b0000 $
1%
b0000 (
b0000 )
b0001 *
b000 +
0,
1.
0/
00
01
02
03
04
05
06
07
08
09
0:
0;
#570000000
0#
0%
#575000000
1#
b0001 $
1%
b0001 (
b0001 )
b0010 *
b001 +
1,
0.
1/
11
12
#580000000
0#
0%
#585000000
1#
b0010 $
1%
b0010 (
b0010 )
b0011 *
b000 +
0,
1.
0/
10
01
12
03
05
06
#590000000
0#
0%
#595000000
1#
b0011 $
1%
b0011 (
b0011 )
b0100 *
b011 +
1,
0.
1/
11
02
13
15
16
#600000000
0#
0%
#605000000
1#
b0100 $
1%
b0100 (
b0100 )
b0101 *
b000 +
0,
1.
0/
00
01
02
03
14
05
16
07
09
0:
