external_components/uart_tx/multiplexer_16_to_1.vhd
library ieee;
use ieee.std_logic_1164.all;

entity multiplexer_16_to_1 is
  port (
    i : in std_logic_vector(15 downto 0);
    selector : in std_logic_vector(3 downto 0);
    o : out std_logic
  );
end multiplexer_16_to_1;

architecture Behavioral of multiplexer_16_to_1 is

begin

  with selector select o <=
    i(0) when "0000",
    i(1) when "0001",
    i(2) when "0010",
    i(3) when "0011",
    i(4) when "0100",
    i(5) when "0101",
    i(6) when "0110",
    i(7) when "0111",
    i(8) when "1000",
    i(9) when "1001",
    i(10) when "1010",
    i(11) when "1011",
    i(12) when "1100",
    i(13) when "1101",
    i(14) when "1110",
    i(15) when "1111",
    'X' when others;

end architecture;

external_components/uart_tx/tb_multiplexer_16_to_1.vhd
library ieee;
use ieee.std_logic_1164.all;
use IEEE.numeric_std.all;

entity tb_multiplexer_16_to_1 is
end tb_multiplexer_16_to_1;

architecture test_bench of tb_multiplexer_16_to_1 is

  component multiplexer_16_to_1 is
    port (
      i : in std_logic_vector(15 downto 0);
      selector : in std_logic_vector(3 downto 0);
      o : out std_logic
    );
  end component;

  signal i : std_logic_vector(15 downto 0);
  signal selector : std_logic_vector(3 downto 0);
  signal o : std_logic;

begin

  used_multiplexer_16_to_1 : multiplexer_16_to_1 port map(
    i => i,
    selector => selector,
    o => o
  );

  process
  begin
    i <= "0000000000000000";
    selector <= "0000";
    wait for 10 ns;
    i(0) <= '1';
    wait for 10 ns;

    i <= "0000000000000000";
    selector <= "0001";
    wait for 10 ns;
    i(1) <= '1';
    wait for 10 ns;

    i <= "0000000000000000";
    selector <= "0010";
    wait for 10 ns;
    i(2) <= '1';
    wait for 10 ns;

    i <= "0000000000000000";
    selector <= "0011";
    wait for 10 ns;
    i(3) <= '1';
    wait for 10 ns;

    i <= "0000000000000000";
    selector <= "0100";
    wait for 10 ns;
    i(4) <= '1';
    wait for 10 ns;

    i <= "0000000000000000";
    selector <= "0101";
    wait for 10 ns;
    i(5) <= '1';
    wait for 10 ns;

    i <= "0000000000000000";
    selector <= "0110";
    wait for 10 ns;
    i(6) <= '1';
    wait for 10 ns;

    i <= "0000000000000000";
    selector <= "0111";
    wait for 10 ns;
    i(7) <= '1';
    wait for 10 ns;

    i <= "0000000000000000";
    selector <= "1000";
    wait for 10 ns;
    i(8) <= '1';
    wait for 10 ns;

    i <= "0000000000000000";
    selector <= "1001";
    wait for 10 ns;
    i(9) <= '1';
    wait for 10 ns;

    i <= "0000000000000000";
    selector <= "1010";
    wait for 10 ns;
    i(10) <= '1';
    wait for 10 ns;

    i <= "0000000000000000";
    selector <= "1011";
    wait for 10 ns;
    i(11) <= '1';
    wait for 10 ns;

    i <= "0000000000000000";
    selector <= "1100";
    wait for 10 ns;
    i(12) <= '1';
    wait for 10 ns;

    i <= "0000000000000000";
    selector <= "1101";
    wait for 10 ns;
    i(13) <= '1';
    wait for 10 ns;

    i <= "0000000000000000";
    selector <= "1110";
    wait for 10 ns;
    i(14) <= '1';
    wait for 10 ns;

    i <= "0000000000000000";
    selector <= "1111";
    wait for 10 ns;
    i(15) <= '1';
    wait for 10 ns;

    wait;
  end process;

end architecture;

external_components/uart_tx/tb_multiplexer_16_to_1.vcd
$date
  Mon Feb  1 21:21:12 2021
$end
$version
  GHDL v0
$end
$timescale
  1 fs
$end
$scope module standard $end
$upscope $end
$scope module std_logic_1164 $end
$upscope $end
$scope module numeric_std $end
$upscope $end
$scope module tb_multiplexer_16_to_1 $end
$var reg 16 ! i[15:0] $end
$var reg 4 " selector[3:0] $end
$var reg 1 # o $end
$scope module used_multiplexer_16_to_1 $end
$var reg 16 $ i[15:0] $end
$var reg 4 % selector[3:0] $end
$var reg 1 & o $end
$upscope $end
$upscope $end
$enddefinitions $end
#0
b0000000000000000 !
b0000 "
0#
b0000000000000000 $
b0000 %
0&
#10000000
b0000000000000001 !
1#
b0000000000000001 $
1&
#20000000
b0000000000000000 !
b0001 "
0#
b0000000000000000 $
b0001 %
0&
#30000000
b0000000000000010 !
1#
b0000000000000010 $
1&
#40000000
b0000000000000000 !
b0010 "
0#
b0000000000000000 $
b0010 %
0&
#50000000
b0000000000000100 !
1#
b0000000000000100 $
1&
#60000000
b0000000000000000 !
b0011 "
0#
b0000000000000000 $
b0011 %
0&
#70000000
b0000000000001000 !
1#
b0000000000001000 $
1&
#80000000
b0000000000000000 !
b0100 "
0#
b0000000000000000 $
b0100 %
0&
#90000000
b0000000000010000 !
1#
b0000000000010000 $
1&
#100000000
b0000000000000000 !
b0101 "
0#
b0000000000000000 $
b0101 %
0&
#110000000
b0000000000100000 !
1#
b0000000000100000 $
1&
#120000000
b0000000000000000 !
b0110 "
0#
b0000000000000000 $
b0110 %
0&
#130000000
b0000000001000000 !
1#
b0000000001000000 $
1&
#140000000
b0000000000000000 !
b0111 "
0#
b0000000000000000 $
b0111 %
0&
#150000000
b0000000010000000 !
1#
b0000000010000000 $
1&
#160000000
b0000000000000000 !
b1000 "
0#
b0000000000000000 $
b1000 %
0&
#170000000
b0000000100000000 !
1#
b0000000100000000 $
1&
#180000000
b0000000000000000 !
b1001 "
0#
b0000000000000000 $
b1001 %
0&
#190000000
b0000001000000000 !
1#
b0000001000000000 $
1&
#200000000
b0000000000000000 !
b1010 "
0#
b0000000000000000 $
b1010 %
0&
#210000000
b0000010000000000 !
1#
b0000010000000000 $
1&
#220000000
b0000000000000000 !
b1011 "
0#
b0000000000000000 $
b1011 %
0&
#230000000
b0000100000000000 !
1#
b0000100000000000 $
1&
#240000000
b0000000000000000 !
b1100 "
0#
b0000000000000000 $
b1100 %
0&
#250000000
b0001000000000000 !
1#
b0001000000000000 $
1&
#260000000
b0000000000000000 !
b1101 "
0#
b0000000000000000 $
b1101 %
0&
#270000000
b0010000000000000 !
1#
b0010000000000000 $
1&
#280000000
b0000000000000000 !
b1110 "
0#
b0000000000000000 $
b1110 %
0&
#290000000
b0100000000000000 !
1#
b0100000000000000 $
1&
#300000000
b0000000000000000 !
b1111 "
0#
b0000000000000000 $
b1111 %
0&
#310000000
b1000000000000000 !
1#
b1000000000000000 $
1&
