external_components/uart_tx/multiplexer_16_to_1.vhd
library ieee;
use ieee.std_logic_1164.all;

entity multiplexer_16_to_1 is
  port (
    i : in std_logic_vector(15 downto 0);
    selector : in std_logic_vector(3 downto 0);
    o : out std_logic
  );
end multiplexer_16_to_1;

architecture Behavioral of multiplexer_16_to_1 is

begin

  with selector select o <=
    i(0) when "0000",
    i(1) when "0001",
    i(2) when "0010",
    i(3) when "0011",
    i(4) when "0100",
    i(5) when "0101",
    i(6) when "0110",
    i(7) when "0111",
    i(8) when "1000",
    i(9) when "1001",
    i(10) when "1010",
    i(11) when "1011",
    i(12) when "1100",
    i(13) when "1101",
    i(14) when "1110",
    i(15) when "1111",
    'X' when others;

end architecture;

external_components/uart_tx/address_decoder.vhd
library ieee;
use ieee.std_logic_1164.all;

entity address_decoder is
 port (
  address_bus : in std_logic_vector(15 downto 0);
  xc000 : out std_logic;
  xc001 : out std_logic
 );
end address_decoder;

architecture Behavioral of address_decoder is

  signal common_15_msb : std_logic;

begin

  common_15_msb <= address_bus(15) AND address_bus(14) AND
                   (NOT address_bus(13)) AND (NOT address_bus(12)) AND
                   (NOT address_bus(11)) AND (NOT address_bus(10)) AND
                   (NOT address_bus(9)) AND (NOT address_bus(8)) AND
                   (NOT address_bus(7)) AND (NOT address_bus(6)) AND
                   (NOT address_bus(5)) AND (NOT address_bus(4)) AND
                   (NOT address_bus(3)) AND (NOT address_bus(2)) AND
                   (NOT address_bus(1));

  xc000 <= common_15_msb AND (NOT address_bus(0));

  xc001 <= common_15_msb AND address_bus(0);

end architecture;

CPU/PC/half_adder.vhd
library ieee;
use ieee.std_logic_1164.all;

entity half_adder is
	port
	(
			a: in std_logic;
			c_in: in std_logic;
			o: out std_logic;
			c_out: out std_logic
	 );
end half_adder;

architecture Behavioral of half_adder is
begin
	o <= a XOR c_in;
	c_out <= a AND c_in;
end Behavioral;

external_components/uart_tx/counter_4_bits.vhd
library ieee;
use ieee.std_logic_1164.all;

entity counter_4_bits is
  port (
    clk : in std_logic;
    clk_enable : in std_logic;
    reset : in std_logic;
    counter_value : out std_logic_vector(3 downto 0)
  );
end counter_4_bits;

architecture Behavioral of counter_4_bits is

  component half_adder is
    port
  	(
  			a: in std_logic;
  			c_in: in std_logic;
  			o: out std_logic;
  			c_out: out std_logic
  	 );
  end component;

  signal current_value : std_logic_vector(3 downto 0) := "1011";
  signal next_value : std_logic_vector(3 downto 0);
  signal carries : std_logic_vector(2 downto 0);

begin

  counter_value <= current_value;

  ha0 : half_adder port map(
    a => current_value(0),
    c_in => '1',
    o => next_value(0),
    c_out => carries(0)
  );

  ha1 : half_adder port map(
    a => current_value(1),
    c_in => carries(0),
    o => next_value(1),
    c_out => carries(1)
  );

  ha2 : half_adder port map(
    a => current_value(2),
    c_in => carries(1),
    o => next_value(2),
    c_out => carries(2)
  );

  ha3 : half_adder port map(
    a => current_value(3),
    c_in => carries(2),
    o => next_value(3),
    c_out => open
  );

  process(clk)
  begin
    if rising_edge(clk) then
      if reset='1' then
        current_value <= "0000";
      else
        if clk_enable='1' then
          current_value <= next_value;
        end if;
      end if;
    end if;
  end process;

end architecture;

external_components/uart_tx/memory_clk_state_machine.vhd
library ieee;
use ieee.std_logic_1164.all;

entity memory_clk_state_machine is
  port (
    memory_clk : in std_logic;
    reset : in std_logic;
    new_request : in std_logic;
    uart_machine_running : in std_logic;
    busy_flag : out std_logic;
    reset_uart_machine : out std_logic;
    data_register_clk_enable : out std_logic
  );
end memory_clk_state_machine;

architecture Behavioral of memory_clk_state_machine is

  signal current_state : std_logic_vector(2 downto 0) := "001";
  signal next_state : std_logic_vector(2 downto 0);

  -- 001 for idle state, 010 for startup state, 100 for running state

begin

  busy_flag <= current_state(1) OR current_state(2);

  reset_uart_machine <= current_state(1);

  data_register_clk_enable <= current_state(0) AND new_request;

  next_state(0) <= (current_state(0) AND (NOT new_request)) OR (current_state(2) AND (NOT uart_machine_running));
  next_state(1) <= (current_state(0) AND new_request) OR (current_state(1) AND (NOT uart_machine_running));
  next_state(2) <= (current_state(1) OR current_state(2)) AND uart_machine_running;

  process(memory_clk)
  begin
    if rising_edge(memory_clk) then
      if reset='1' then
        current_state <= "001";
      else
        current_state <= next_state;
      end if;
    end if;
  end process;

end architecture;

external_components/uart_tx/uart_tx.vhd
library ieee;
use ieee.std_logic_1164.all;

entity uart_tx is
  port(
    memory_clk : in std_logic;
    uart_clk : in std_logic;
    reset : in std_logic;
    memory_wren : in std_logic;
    memory_address : in std_logic_vector(31 downto 0);
    memory_in_bus : in std_logic_vector(31 downto 0);
    uart_out_bus : out std_logic_vector(31 downto 0);
    tx : out std_logic
  );
end uart_tx;

architecture Behavioral of uart_tx is

  component memory_clk_state_machine is
    port (
      memory_clk : in std_logic;
      reset : in std_logic;
      new_request : in std_logic;
      uart_machine_running : in std_logic;
      busy_flag : out std_logic;
      reset_uart_machine : out std_logic;
      data_register_clk_enable : out std_logic
    );
  end component;

  component counter_4_bits is
    port (
      clk : in std_logic;
      clk_enable : in std_logic;
      reset : in std_logic;
      counter_value : out std_logic_vector(3 downto 0)
    );
  end component;

  component address_decoder is
    port (
     address_bus : in std_logic_vector(15 downto 0);
     xc000 : out std_logic;
     xc001 : out std_logic
    );
  end component;

  component multiplexer_16_to_1 is
    port (
      i : in std_logic_vector(15 downto 0);
      selector : in std_logic_vector(3 downto 0);
      o : out std_logic
    );
  end component;

  signal memory_address_register : std_logic_vector(15 downto 0);
  signal memory_wren_register : std_logic := '0';
  signal memory_data_register : std_logic_vector(7 downto 0);
  signal counter_value : std_logic_vector(3 downto 0);
  signal mux_input : std_logic_vector(15 downto 0) := "1111111111111100";
  signal internal_reset : std_logic;
  signal mux_output : std_logic;
  signal data_register_clk_enable : std_logic;
  signal output_register_clk_enable : std_logic;
  signal counter_clk_enable : std_logic;
  signal is_counter_0000 : std_logic;
  signal is_counter_1011 : std_logic;
  signal is_address_xc000 : std_logic;
  signal is_address_xc001 : std_logic;
  signal busy_flag : std_logic;
  signal tx_signal : std_logic := '1';
  signal memory_address_real : std_logic_vector(15 downto 0);
  signal new_request : std_logic;
  signal reset_uart_machine : std_logic;
  -- signal counter_reset : std_logic := '0';

begin

  memory_address_real <= memory_address(15 downto 0);

  mux_input(15 downto 10) <= "111111";
  mux_input(1 downto 0) <= "00";

  is_counter_0000 <= (NOT counter_value(3)) AND (NOT counter_value(2)) AND (NOT counter_value(1)) AND (NOT counter_value(0));

  is_counter_1011 <= counter_value(3) AND (NOT counter_value(2)) AND counter_value(1) AND counter_value(0);

  output_register_clk_enable <= (NOT is_counter_0000) AND (NOT is_counter_1011);

  new_request <= memory_wren_register AND is_address_xc000;

  counter_clk_enable <= NOT is_counter_1011;

  internal_reset <= reset_uart_machine;

  tx <= tx_signal;

  memory_clk_state_machine_instance : memory_clk_state_machine port map (
    memory_clk => memory_clk,
    reset => reset,
    new_request => new_request,
    uart_machine_running => counter_clk_enable,
    busy_flag => busy_flag,
    reset_uart_machine => reset_uart_machine,
    data_register_clk_enable => data_register_clk_enable
  );

  counter : counter_4_bits port map(
    clk => uart_clk,
    clk_enable => counter_clk_enable,
    reset => internal_reset,
    -- reset => counter_reset,
    counter_value => counter_value
  );

  decoder : address_decoder port map(
    address_bus => memory_address_register,
    xc000 => is_address_xc000,
    xc001 => is_address_xc001
  );

  multiplexer : multiplexer_16_to_1 port map(
    i => mux_input,
    selector => counter_value,
    o => mux_output
  );

  process(uart_clk)
  begin
    if rising_edge(uart_clk) then
      if output_register_clk_enable='1' then
        tx_signal <= mux_output;
      end if;
    end if;
  end process;

  process(memory_clk)
  begin
    if rising_edge(memory_clk) then
      memory_address_register <= memory_address_real;
      memory_data_register <= memory_in_bus(7 downto 0);
    end if;
  end process;

  process(memory_clk)
  begin
    if rising_edge(memory_clk) then
      if reset='1' then
        memory_wren_register <= '0';
      else
        memory_wren_register <= memory_wren;
      end if;
    end if;
  end process;

  process(memory_clk)
  begin
    if rising_edge(memory_clk) then
      if data_register_clk_enable='1' then
        mux_input(9 downto 2) <= memory_data_register;
      end if;
    end if;
  end process;

  uart_out_bus(8) <= busy_flag AND is_address_xc001;
  uart_out_bus(31 downto 9) <= (others => '0');
  uart_out_bus(7 downto 0) <= (others => '0');

end architecture;

external_components/uart_tx/tb_uart_tx.vhd
library ieee;
use ieee.std_logic_1164.all;
use IEEE.numeric_std.all;

entity tb_uart_tx is
end tb_uart_tx;

architecture test_bench of tb_uart_tx is

  component uart_tx is
    port(
      memory_clk : in std_logic;
      uart_clk : in std_logic;
      reset : in std_logic;
      memory_wren : in std_logic;
      memory_address : in std_logic_vector(31 downto 0);
      memory_in_bus : in std_logic_vector(31 downto 0);
      uart_out_bus : out std_logic_vector(31 downto 0);
      tx : out std_logic
    );
  end component;

  signal memory_wren, uart_clk, memory_clk : std_logic;
  signal reset : std_logic;
  signal memory_address : std_logic_vector(31 downto 0);
  signal memory_in_bus : std_logic_vector(31 downto 0);
  signal uart_out_bus : std_logic_vector(31 downto 0);
  signal tx : std_logic;

begin

  used_uart_tx : uart_tx port map(
    memory_clk => memory_clk,
    uart_clk => uart_clk,
    reset => reset,
    memory_wren => memory_wren,
    memory_address => memory_address,
    memory_in_bus => memory_in_bus,
    uart_out_bus => uart_out_bus,
    tx => tx
  );

  process
  begin
    uart_clk <= '0';
    wait for 10 ns;
    uart_clk <= '1';
    wait for 10 ns;
  end process;

  process
  begin
    memory_clk <= '0';
    wait for 5 ns;
    memory_clk <= '1';
    wait for 5 ns;
  end process;

  process
  begin
    memory_address(31 downto 16) <= "XXXXXXXXXXXXXXXX";
    memory_in_bus(31 downto 8) <= "XXXXXXXXXXXXXXXXXXXXXXXX";
    -- reset <= '1';
    -- wait for 20 ns;
    reset <= '0';

    memory_wren <= '0';
    memory_address(15 downto 0) <= "0000000000000000";
    memory_in_bus(7 downto 0) <= "01011000";

    wait for 50 ns;

    memory_address(15 downto 0) <= "1100000000000001";
    wait for 10 ns;

    memory_address(15 downto 0) <= "1100000000000000";
    memory_in_bus(7 downto 0) <= "01011000";
    wait for 10 ns;

    memory_wren <= '1';
    wait for 10 ns;

    memory_address(15 downto 0) <= "1100000000000001";
    memory_wren <= '0';
    wait for 500 ns;

    memory_address(15 downto 0) <= "1100000000000001";
    wait for 10 ns;

    memory_address(15 downto 0) <= "1100000000000000";
    memory_in_bus(7 downto 0) <= "01011000";
    wait for 10 ns;

    memory_wren <= '1';
    wait for 10 ns;

    memory_address(15 downto 0) <= "1100000000000000";
    memory_in_bus(7 downto 0) <= "01011000";
    memory_wren <= '1';
    wait for 10 ns;

    memory_address(15 downto 0) <= "1100000000000001";
    memory_in_bus(7 downto 0) <= "01011000";
    memory_wren <= '0';
    wait for 10 ns;

    memory_wren <= '0';
    wait for 200 ns;

    wait;
  end process;

end architecture;

external_components/uart_tx/tb_uart_tx.vcd
$date
  Tue Feb 16 13:35:15 2021
$end
$version
  GHDL v0
$end
$timescale
  1 fs
$end
$scope module standard $end
$upscope $end
$scope module std_logic_1164 $end
$upscope $end
$scope module numeric_std $end
$upscope $end
$scope module tb_uart_tx $end
$var reg 1 ! memory_wren $end
$var reg 1 " uart_clk $end
$var reg 1 # memory_clk $end
$var reg 1 $ reset $end
$var reg 32 % memory_address[31:0] $end
$var reg 32 & memory_in_bus[31:0] $end
$var reg 32 ' uart_out_bus[31:0] $end
$var reg 1 ( tx $end
$scope module used_uart_tx $end
$var reg 1 ) memory_clk $end
$var reg 1 * uart_clk $end
$var reg 1 + reset $end
$var reg 1 , memory_wren $end
$var reg 32 - memory_address[31:0] $end
$var reg 32 . memory_in_bus[31:0] $end
$var reg 32 / uart_out_bus[31:0] $end
$var reg 1 0 tx $end
$var reg 16 1 memory_address_register[15:0] $end
$var reg 1 2 memory_wren_register $end
$var reg 8 3 memory_data_register[7:0] $end
$var reg 4 4 counter_value[3:0] $end
$var reg 16 5 mux_input[15:0] $end
$var reg 1 6 internal_reset $end
$var reg 1 7 mux_output $end
$var reg 1 8 data_register_clk_enable $end
$var reg 1 9 output_register_clk_enable $end
$var reg 1 : counter_clk_enable $end
$var reg 1 ; is_counter_0000 $end
$var reg 1 < is_counter_1011 $end
$var reg 1 = is_address_xc000 $end
$var reg 1 > is_address_xc001 $end
$var reg 1 ? busy_flag $end
$var reg 1 @ tx_signal $end
$var reg 16 A memory_address_real[15:0] $end
$var reg 1 B new_request $end
$var reg 1 C reset_uart_machine $end
$scope module memory_clk_state_machine_instance $end
$var reg 1 D memory_clk $end
$var reg 1 E reset $end
$var reg 1 F new_request $end
$var reg 1 G uart_machine_running $end
$var reg 1 H busy_flag $end
$var reg 1 I reset_uart_machine $end
$var reg 1 J data_register_clk_enable $end
$var reg 3 K current_state[2:0] $end
$var reg 3 L next_state[2:0] $end
$upscope $end
$scope module counter $end
$var reg 1 M clk $end
$var reg 1 N clk_enable $end
$var reg 1 O reset $end
$var reg 4 P counter_value[3:0] $end
$var reg 4 Q current_value[3:0] $end
$var reg 4 R next_value[3:0] $end
$var reg 3 S carries[2:0] $end
$scope module ha0 $end
$var reg 1 T a $end
$var reg 1 U c_in $end
$var reg 1 V o $end
$var reg 1 W c_out $end
$upscope $end
$scope module ha1 $end
$var reg 1 X a $end
$var reg 1 Y c_in $end
$var reg 1 Z o $end
$var reg 1 [ c_out $end
$upscope $end
$scope module ha2 $end
$var reg 1 \ a $end
$var reg 1 ] c_in $end
$var reg 1 ^ o $end
$var reg 1 _ c_out $end
$upscope $end
$scope module ha3 $end
$var reg 1 ` a $end
$var reg 1 a c_in $end
$var reg 1 b o $end
$var reg 1 c c_out $end
$upscope $end
$upscope $end
$scope module decoder $end
$var reg 16 d address_bus[15:0] $end
$var reg 1 e xc000 $end
$var reg 1 f xc001 $end
$var reg 1 g common_15_msb $end
$upscope $end
$scope module multiplexer $end
$var reg 16 h i[15:0] $end
$var reg 4 i selector[3:0] $end
$var reg 1 j o $end
$upscope $end
$upscope $end
$upscope $end
$enddefinitions $end
#0
0!
0"
0#
0$
bXXXXXXXXXXXXXXXX0000000000000000 %
bXXXXXXXXXXXXXXXXXXXXXXXX01011000 &
b00000000000000000000000000000000 '
1(
0)
0*
0+
0,
bXXXXXXXXXXXXXXXX0000000000000000 -
bXXXXXXXXXXXXXXXXXXXXXXXX01011000 .
b00000000000000000000000000000000 /
10
bUUUUUUUUUUUUUUUU 1
02
bUUUUUUUU 3
b1011 4
b1111111111111100 5
06
17
08
09
0:
0;
1<
U=
U>
0?
1@
b0000000000000000 A
0B
0C
0D
0E
0F
0G
0H
0I
0J
b001 K
b001 L
0M
0N
0O
b1011 P
b1011 Q
b1100 R
b011 S
1T
1U
0V
1W
1X
1Y
0Z
1[
0\
1]
1^
0_
1`
0a
1b
0c
bUUUUUUUUUUUUUUUU d
Ue
Uf
Ug
b1111111111111100 h
b1011 i
1j
#5000000
1#
1)
b0000000000000000 1
b01011000 3
0=
0>
1D
b0000000000000000 d
0e
0f
0g
#10000000
1"
0#
0)
1*
0D
1M
#15000000
1#
1)
1D
#20000000
0"
0#
0)
0*
0D
0M
#25000000
1#
1)
1D
#30000000
1"
0#
0)
1*
0D
1M
#35000000
1#
1)
1D
#40000000
0"
0#
0)
0*
0D
0M
#45000000
1#
1)
1D
#50000000
1"
0#
bXXXXXXXXXXXXXXXX1100000000000001 %
0)
1*
bXXXXXXXXXXXXXXXX1100000000000001 -
b1100000000000001 A
0D
1M
#55000000
1#
1)
b1100000000000001 1
1>
1D
b1100000000000001 d
1f
1g
#60000000
0"
0#
bXXXXXXXXXXXXXXXX1100000000000000 %
0)
0*
bXXXXXXXXXXXXXXXX1100000000000000 -
b1100000000000000 A
0D
0M
#65000000
1#
1)
b1100000000000000 1
1=
0>
1D
b1100000000000000 d
1e
0f
#70000000
1!
1"
0#
0)
1*
1,
0D
1M
#75000000
1#
1)
12
18
1B
1D
1F
1J
b010 L
#80000000
0!
0"
0#
bXXXXXXXXXXXXXXXX1100000000000001 %
0)
0*
0,
bXXXXXXXXXXXXXXXX1100000000000001 -
b1100000000000001 A
0D
0M
#85000000
1#
b00000000000000000000000000000001 '
1)
b00000000000000000000000000000001 /
b1100000000000001 1
02
b1111110101100000 5
16
08
0=
1>
1?
0B
1C
1D
0F
1H
1I
0J
b010 K
1O
b1100000000000001 d
0e
1f
b1111110101100000 h
#90000000
1"
0#
0)
1*
b0000 4
07
1:
1;
0<
0D
1G
b100 L
1M
1N
b0000 P
b0000 Q
b0001 R
b000 S
0T
1V
0W
0X
0Y
0Z
0[
0]
0^
0`
0b
b0000 i
0j
#95000000
1#
1)
06
0C
1D
0I
b100 K
0O
#100000000
0"
0#
0)
0*
0D
0M
#105000000
1#
1)
1D
#110000000
1"
0#
0)
1*
b0001 4
19
0;
0D
1M
b0001 P
b0001 Q
b0010 R
b001 S
1T
0V
1W
1Y
1Z
b0001 i
#115000000
1#
1)
1D
#120000000
0"
0#
0)
0*
0D
0M
#125000000
1#
1)
1D
#130000000
1"
0#
0(
0)
1*
00
b0010 4
0@
0D
1M
b0010 P
b0010 Q
b0011 R
b000 S
0T
1V
0W
1X
0Y
1Z
0[
0]
0^
b0010 i
#135000000
1#
1)
1D
#140000000
0"
0#
0)
0*
0D
0M
#145000000
1#
1)
1D
#150000000
1"
0#
0)
1*
b0011 4
0D
1M
b0011 P
b0011 Q
b0100 R
b011 S
1T
0V
1W
1Y
0Z
1[
1]
1^
b0011 i
#155000000
1#
1)
1D
#160000000
0"
0#
0)
0*
0D
0M
#165000000
1#
1)
1D
#170000000
1"
0#
0)
1*
b0100 4
0D
1M
b0100 P
b0100 Q
b0101 R
b000 S
0T
1V
0W
0X
0Y
0Z
0[
1\
0]
1^
0_
0a
0b
b0100 i
#175000000
1#
1)
1D
#180000000
0"
0#
0)
0*
0D
0M
#185000000
1#
1)
1D
#190000000
1"
0#
0)
1*
b0101 4
17
0D
1M
b0101 P
b0101 Q
b0110 R
b001 S
1T
0V
1W
1Y
1Z
b0101 i
1j
#195000000
1#
1)
1D
#200000000
0"
0#
0)
0*
0D
0M
#205000000
1#
1)
1D
#210000000
1"
0#
1(
0)
1*
10
b0110 4
1@
0D
1M
b0110 P
b0110 Q
b0111 R
b000 S
0T
1V
0W
1X
0Y
1Z
0[
0]
1^
0_
0a
0b
b0110 i
#215000000
1#
1)
1D
#220000000
0"
0#
0)
0*
0D
0M
#225000000
1#
1)
1D
#230000000
1"
0#
0)
1*
b0111 4
07
0D
1M
b0111 P
b0111 Q
b1000 R
b111 S
1T
0V
1W
1Y
0Z
1[
1]
0^
1_
1a
1b
b0111 i
0j
#235000000
1#
1)
1D
#240000000
0"
0#
0)
0*
0D
0M
#245000000
1#
1)
1D
#250000000
1"
0#
0(
0)
1*
00
b1000 4
17
0@
0D
1M
b1000 P
b1000 Q
b1001 R
b000 S
0T
1V
0W
0X
0Y
0Z
0[
0\
0]
0^
0_
1`
0a
1b
0c
b1000 i
1j
#255000000
1#
1)
1D
#260000000
0"
0#
0)
0*
0D
0M
#265000000
1#
1)
1D
#270000000
1"
0#
1(
0)
1*
10
b1001 4
07
1@
0D
1M
b1001 P
b1001 Q
b1010 R
b001 S
1T
0V
1W
1Y
1Z
b1001 i
0j
#275000000
1#
1)
1D
#280000000
0"
0#
0)
0*
0D
0M
#285000000
1#
1)
1D
#290000000
1"
0#
0(
0)
1*
00
b1010 4
17
0@
0D
1M
b1010 P
b1010 Q
b1011 R
b000 S
0T
1V
0W
1X
0Y
1Z
0[
0]
0^
b1010 i
1j
#295000000
1#
1)
1D
#300000000
0"
0#
0)
0*
0D
0M
#305000000
1#
1)
1D
#310000000
1"
0#
1(
0)
1*
10
b1011 4
09
0:
1<
1@
0D
0G
b001 L
1M
0N
b1011 P
b1011 Q
b1100 R
b011 S
1T
0V
1W
1Y
0Z
1[
1]
1^
b1011 i
#315000000
1#
b00000000000000000000000000000000 '
1)
b00000000000000000000000000000000 /
0?
1D
0H
b001 K
